{
  "jobId": "job_20260429025903_ptq94i",
  "tasks": [
    {
      "id": "job_20260429025903_ptq94i__noizekid",
      "jobId": "job_20260429025903_ptq94i",
      "targetKey": "artist:noizekid",
      "targetType": "artist",
      "slug": "noizekid-mexican-moombahton-dancehall-producer",
      "sourceRef": {
        "kind": "artist_catalog",
        "artistSlug": "noizekid",
        "artistName": "Noizekid"
      },
      "status": "needs_review",
      "draftPath": "data\\editorial\\jobs\\job_20260429025903_ptq94i\\articles\\job_20260429025903_ptq94i__noizekid.draft.json",
      "enrichedPath": "data\\editorial\\jobs\\job_20260429025903_ptq94i\\articles\\job_20260429025903_ptq94i__noizekid.enriched.json",
      "reviewPath": "data\\editorial\\jobs\\job_20260429025903_ptq94i\\articles\\job_20260429025903_ptq94i__noizekid.review.json",
      "groveUri": null,
      "groveGatewayUrl": null,
      "groveStorageKey": null,
      "error": null,
      "attempts": 1,
      "updatedAt": "2026-04-29T02:59:11.322Z"
    }
  ]
}
