{
  "id": "job_20260429035921_k1tkrx",
  "mode": "single",
  "source": "existing_db",
  "targetType": "artist",
  "filters": {
    "artistSlugs": [],
    "genre": null,
    "scene": null,
    "city": null,
    "missingOnly": false
  },
  "count": 1,
  "concurrency": 1,
  "status": "completed",
  "createdAt": "2026-04-29T03:59:21.440Z",
  "updatedAt": "2026-04-29T03:59:28.460Z",
  "completedAt": "2026-04-29T03:59:28.460Z",
  "createdBy": "owner",
  "promptProfile": {
    "writerProfile": "default",
    "editorProfile": "default"
  },
  "notes": "Artist catalog generation for Noizekid"
}
