{
  "jobId": "job_20260429002137_8qy4rv",
  "tasks": [
    {
      "id": "job_20260429002137_8qy4rv__noizekid",
      "jobId": "job_20260429002137_8qy4rv",
      "targetKey": "artist:noizekid",
      "targetType": "artist",
      "slug": "noizekid-mexican-moombahton-dancehall-producer",
      "sourceRef": {
        "kind": "artist_catalog",
        "artistSlug": "noizekid",
        "artistName": "Noizekid"
      },
      "status": "needs_review",
      "draftPath": "data\\editorial\\jobs\\job_20260429002137_8qy4rv\\articles\\job_20260429002137_8qy4rv__noizekid.draft.json",
      "enrichedPath": "data\\editorial\\jobs\\job_20260429002137_8qy4rv\\articles\\job_20260429002137_8qy4rv__noizekid.enriched.json",
      "reviewPath": "data\\editorial\\jobs\\job_20260429002137_8qy4rv\\articles\\job_20260429002137_8qy4rv__noizekid.review.json",
      "groveUri": null,
      "groveGatewayUrl": null,
      "groveStorageKey": null,
      "error": null,
      "attempts": 2,
      "updatedAt": "2026-04-29T00:22:54.758Z"
    }
  ]
}
